odoo/addons/ssi_l10n_id_taxform_bukti_potong_pph_1721_a1/README.rst
odoo/addons/ssi_l10n_id_taxform_bukti_potong_pph_1721_a1/__init__.py
odoo/addons/ssi_l10n_id_taxform_bukti_potong_pph_1721_a1/__manifest__.py
odoo/addons/ssi_l10n_id_taxform_bukti_potong_pph_1721_a1/data/approval_template_data.xml
odoo/addons/ssi_l10n_id_taxform_bukti_potong_pph_1721_a1/data/ir_sequence_data.xml
odoo/addons/ssi_l10n_id_taxform_bukti_potong_pph_1721_a1/data/policy_template_data.xml
odoo/addons/ssi_l10n_id_taxform_bukti_potong_pph_1721_a1/data/sequence_template_data.xml
odoo/addons/ssi_l10n_id_taxform_bukti_potong_pph_1721_a1/i18n/ssi_l10n_id_taxform_bukti_potong_pph_1721_a1.pot
odoo/addons/ssi_l10n_id_taxform_bukti_potong_pph_1721_a1/models/__init__.py
odoo/addons/ssi_l10n_id_taxform_bukti_potong_pph_1721_a1/models/bukti_potong_pph_1721_a1.py
odoo/addons/ssi_l10n_id_taxform_bukti_potong_pph_1721_a1/models/bukti_potong_pph_1721_a1_config.py
odoo/addons/ssi_l10n_id_taxform_bukti_potong_pph_1721_a1/models/res_company.py
odoo/addons/ssi_l10n_id_taxform_bukti_potong_pph_1721_a1/reports/bukti_potong_pph_1721_a1.odt
odoo/addons/ssi_l10n_id_taxform_bukti_potong_pph_1721_a1/reports/bukti_potong_pph_1721_a1_report.xml
odoo/addons/ssi_l10n_id_taxform_bukti_potong_pph_1721_a1/security/ir.model.access.csv
odoo/addons/ssi_l10n_id_taxform_bukti_potong_pph_1721_a1/security/ir_module_category_data.xml
odoo/addons/ssi_l10n_id_taxform_bukti_potong_pph_1721_a1/security/ir_rule_data.xml
odoo/addons/ssi_l10n_id_taxform_bukti_potong_pph_1721_a1/security/res_group_data.xml
odoo/addons/ssi_l10n_id_taxform_bukti_potong_pph_1721_a1/static/description/icon.png
odoo/addons/ssi_l10n_id_taxform_bukti_potong_pph_1721_a1/views/bukti_potong_pph_1721_a1_config_views.xml
odoo/addons/ssi_l10n_id_taxform_bukti_potong_pph_1721_a1/views/bukti_potong_pph_1721_a1_views.xml
odoo/addons/ssi_l10n_id_taxform_bukti_potong_pph_1721_a1/views/res_company_views.xml
odoo14_addon_ssi_l10n_id_taxform_bukti_potong_pph_1721_a1-14.0.1.2.0.dist-info/METADATA
odoo14_addon_ssi_l10n_id_taxform_bukti_potong_pph_1721_a1-14.0.1.2.0.dist-info/WHEEL
odoo14_addon_ssi_l10n_id_taxform_bukti_potong_pph_1721_a1-14.0.1.2.0.dist-info/top_level.txt
odoo14_addon_ssi_l10n_id_taxform_bukti_potong_pph_1721_a1-14.0.1.2.0.dist-info/RECORD
