Metadata-Version: 2.1
Name: odoo14-addon-ssi_l10n_id_taxform_bukti_potong_pph_1721_a1
Version: 14.0.1.2.0
Summary: Indonesia - Bukti Potong PPh 21 Formulir 1721 A1
Home-page: https://simetri-sinergi.id
Author: PT. Simetri Sinergi Indonesia, OpenSynergy Indonesia
License: AGPL-3
Classifier: Programming Language :: Python
Classifier: Framework :: Odoo
Classifier: Framework :: Odoo :: 14.0
Classifier: License :: OSI Approved :: GNU Affero General Public License v3
Requires-Python: >=3.6
Requires-Dist: odoo14-addon-partner-contact-in-several-companies
Requires-Dist: odoo14-addon-report-py3o
Requires-Dist: odoo14-addon-ssi-l10n-id-partner-identification-kependudukan
Requires-Dist: odoo14-addon-ssi-l10n-id-taxform-bukti-potong-pph-mixin
Requires-Dist: odoo14-addon-ssi-l10n-id-taxform-pph-21
Requires-Dist: odoo14-addon-ssi-partner
Requires-Dist: odoo14-addon-ssi-print-mixin
Requires-Dist: odoo14-addon-ssi-transaction-cancel-mixin
Requires-Dist: odoo14-addon-ssi-transaction-confirm-mixin
Requires-Dist: odoo14-addon-ssi-transaction-done-mixin
Requires-Dist: odoo14-addon-ssi-transaction-mixin
Requires-Dist: odoo<14.1dev,>=14.0a
